odoo10_addon_l10n_nl_bsn-10.0.0.1.0-py2.7-nspkg.pth
odoo/addons/l10n_nl_bsn/__manifest__.py
odoo/addons/l10n_nl_bsn/__init__.py
odoo/addons/l10n_nl_bsn/README.rst
odoo/addons/l10n_nl_bsn/models/res_partner.py
odoo/addons/l10n_nl_bsn/models/__init__.py
odoo/addons/l10n_nl_bsn/views/res_partner.xml
odoo10_addon_l10n_nl_bsn-10.0.0.1.0.dist-info/top_level.txt
odoo10_addon_l10n_nl_bsn-10.0.0.1.0.dist-info/WHEEL
odoo10_addon_l10n_nl_bsn-10.0.0.1.0.dist-info/RECORD
odoo10_addon_l10n_nl_bsn-10.0.0.1.0.dist-info/metadata.json
odoo10_addon_l10n_nl_bsn-10.0.0.1.0.dist-info/DESCRIPTION.rst
odoo10_addon_l10n_nl_bsn-10.0.0.1.0.dist-info/METADATA
odoo10_addon_l10n_nl_bsn-10.0.0.1.0.dist-info/namespace_packages.txt
