Metadata-Version: 2.0
Name: odoo10-addon-l10n-nl-bsn
Version: 10.0.0.1.0
Summary: Burgerservicenummer (BSN) for Partners
Home-page: http://www.onestein.eu
Author: UNKNOWN
Author-email: UNKNOWN
License: AGPL-3
Platform: UNKNOWN
Requires-Dist: odoo (<10.1dev,>=10.0)
Requires-Dist: stdnum
Classifier: Programming Language :: Python :: 2.7
Classifier: Framework :: Odoo
Classifier: License :: OSI Approved :: GNU Affero General Public License v3
